ka_uts_wdp/__init__.py
ka_uts_wdp/__version__.py
ka_uts_wdp/data/__init__.py
ka_uts_wdp/data/srr.yml.old
ka_uts_wdp/data/wdi.yml
ka_uts_wdp/data/wdp.yml
ka_uts_wdp/docs/conf.py
ka_uts_wdp/docs/index.rst
ka_uts_wdp/docs/make.bat
ka_uts_wdp/pmeh/__init__.py
ka_uts_wdp/pmeh/py.typed
ka_uts_wdp/pmeh/wdp.py
ka_uts_wdp-4.1.0.250601.dist-info/licenses/LICENSE.txt
ka_uts_wdp-4.1.0.250601.dist-info/METADATA
ka_uts_wdp-4.1.0.250601.dist-info/WHEEL
ka_uts_wdp-4.1.0.250601.dist-info/top_level.txt
ka_uts_wdp-4.1.0.250601.dist-info/RECORD
