Metadata-Version: 2.4
Name: ka_uts_wdp
Version: 4.1.0.250601
Summary: Watchdog Processors Utilities
Author-email: Bernd Stroehle <bernd.stroehle@gmail.com>
Maintainer-email: Bernd Stroehle <bernd.stroehle@gmail.com>
License-Expression: GPL-3.0-only WITH Classpath-exception-2.0 OR BSD-3-Clause
Project-URL: Source Code, https://github.com/bs29/ka_uts_wdp/tree/master
Project-URL: Homepage, https://kosakya.de/
Project-URL: Documentation, https://ka_uts_wdp.readthedocs.io/en/latest
Project-URL: Apache-2.0 License, https://apache.org/licenses/LICENSE-2.0
Project-URL: GPLv3 License, https://www.gnu.org/licenses/gpl-3.0.en.html
Classifier: Development Status :: 5 - Production/Stable
Classifier: Intended Audience :: Developers
Classifier: Operating System :: OS Independent
Classifier: Programming Language :: Python :: 3.10
Classifier: Natural Language :: English
Classifier: Topic :: Software Development :: Libraries :: Python Modules
Requires-Python: >=3.10
License-File: LICENSE.txt
Requires-Dist: ka_uts_dic>=4.1.0.250525
Requires-Dist: ka_uts_log>=4.1.0.250525
Requires-Dist: ka_uts_path>=4.1.0.250601
Requires-Dist: ka_uts_uts>=4.1.0.250601
Requires-Dist: watchdog>=6.0.0
Dynamic: license-file
